robustbase/__init__.py
robustbase/version.py
robustbase/stats/Qn.py
robustbase/stats/Sn.py
robustbase/stats/__init__.py
robustbase/stats/covComed.py
robustbase/stats/iqr.py
robustbase/stats/mad.py
robustbase/utils/__init__.py
robustbase/utils/mean.py
robustbase/utils/median.py
robustbase-3.1.0.dist-info/LICENSE
robustbase-3.1.0.dist-info/METADATA
robustbase-3.1.0.dist-info/WHEEL
robustbase-3.1.0.dist-info/top_level.txt
robustbase-3.1.0.dist-info/RECORD
