Metadata-Version: 2.1
Name: robustbase
Version: 3.1.0
Summary: A Python Based Library to Calculate Estimators (Sn, Qn, MAD, IQR, covComed)
Home-page: https://github.com/deepak7376/robustbase
Author: Deepak Yadav
Author-email: dky.united@gmail.com
License: MIT
Project-URL: Source, https://github.com/deepak7376/robustbase
Project-URL: Tracker, https://github.com/deepak7376/robustbase/issues
Keywords: robust statistics robustness Sn Qn MAD IQR
Classifier: Development Status :: 3 - Alpha
Classifier: Intended Audience :: Developers
Classifier: License :: OSI Approved :: MIT License
Classifier: Programming Language :: Python :: 3
Classifier: Programming Language :: Python :: 3.6
Classifier: Programming Language :: Python :: 3.7
Classifier: Programming Language :: Python :: 3.8
Classifier: Programming Language :: Python :: 3.9
Requires-Python: >=3.0
License-File: LICENSE
Requires-Dist: certifi >=2019.11.28
Requires-Dist: docutils >=0.15.2
Requires-Dist: numpy >=1.18.0
Requires-Dist: scipy >=1.13.1
Requires-Dist: statistics >=1.0.3.5
Provides-Extra: dev
Requires-Dist: pytest >=6.0.0 ; extra == 'dev'
Requires-Dist: pytest-cov >=2.10.0 ; extra == 'dev'
Requires-Dist: coverage >=5.0 ; extra == 'dev'
Requires-Dist: flake8 >=3.8.0 ; extra == 'dev'
